odoo/addons/web_widget_popover/README.rst
odoo/addons/web_widget_popover/__init__.py
odoo/addons/web_widget_popover/__manifest__.py
odoo/addons/web_widget_popover/i18n/it.po
odoo/addons/web_widget_popover/i18n/web_widget_popover.pot
odoo/addons/web_widget_popover/readme/CONTRIBUTORS.md
odoo/addons/web_widget_popover/readme/DESCRIPTION.md
odoo/addons/web_widget_popover/readme/USAGE.md
odoo/addons/web_widget_popover/static/description/icon.png
odoo/addons/web_widget_popover/static/description/index.html
odoo/addons/web_widget_popover/static/src/popover.esm.js
odoo/addons/web_widget_popover/static/src/popover.xml
odoo_addon_web_widget_popover-18.0.1.0.0.4.dist-info/METADATA
odoo_addon_web_widget_popover-18.0.1.0.0.4.dist-info/WHEEL
odoo_addon_web_widget_popover-18.0.1.0.0.4.dist-info/top_level.txt
odoo_addon_web_widget_popover-18.0.1.0.0.4.dist-info/RECORD
